Metadata-Version: 2.1
Name: TinyAGI
Version: 0.0.2
Summary: TinyAGI is a modular AI agent framework controlled via JSON configuration.
Home-page: https://github.com/SullyGreene/TinyAGI
Author: Sully Greene
Project-URL: Bug Tracker, https://github.com/SullyGreene/TinyAGI/issues
Classifier: Programming Language :: Python :: 3
Classifier: License :: OSI Approved :: MIT License
Classifier: Operating System :: OS Independent
Requires-Python: >=3.8
Requires-Dist: nltk
Requires-Dist: ollama
Requires-Dist: gitpython
Requires-Dist: python-dotenv
Requires-Dist: flask
Requires-Dist: black
